{
    "template": "base.mustache",
    "partials": {
        "body": "index.mustache",
        "header": "header.mustache"
    },
    "meta": {
        "title": "Index page"
    },
    "assets": {
        "styles": [ "index.css" ],
        "scripts": [ "index.js" ]
    },
    "collections": {
        "articles": "articles"
    },
    "common": [
        "header.json"
    ],
    "data": {
        "title": "This this the new index title"
    },
    "markdown": {
        "description": "index/description.md"
    }
}
